hopeit/fs_storage/__init__.py
hopeit/fs_storage/partition.py
hopeit/fs_storage/py.typed
hopeit/fs_storage/events/__init__.py
hopeit/fs_storage/events/py.typed
hopeit/fs_storage/events/stream_batch_storage.py
hopeit_fs_storage-0.28.1.dist-info/METADATA
hopeit_fs_storage-0.28.1.dist-info/WHEEL
hopeit_fs_storage-0.28.1.dist-info/top_level.txt
hopeit_fs_storage-0.28.1.dist-info/RECORD
