Metadata-Version: 2.4
Name: hopeit.fs-storage
Version: 0.28.1
Summary: Hopeit Engine File System Storage Toolkit
Author-email: Leo Smerling & Pablo Canto <contact@hopeit.com.ar>, Leo Smerling <contact@hopeit.com.ar>, Pablo Canto <contact@hopeit.com.ar>
License: Apache-2.0
Project-URL: Homepage, https://github.com/hopeit-git/hopeit.engine
Project-URL: CI: GitHub Actions, https://github.com/hopeit-git/hopeit.engine/actions?query=workflow
Project-URL: Docs: RTD, https://hopeitengine.readthedocs.io/en/latest/
Project-URL: GitHub: issues, https://github.com/hopeit-git/hopeit.engine/issues
Project-URL: GitHub: repo, https://github.com/hopeit-git/hopeit.engine
Classifier: Intended Audience :: Developers
Classifier: Programming Language :: Python
Classifier: Programming Language :: Python :: 3.10
Classifier: Programming Language :: Python :: 3.11
Classifier: Programming Language :: Python :: 3.12
Classifier: Programming Language :: Python :: 3.13
Classifier: Programming Language :: Python :: 3.14
Classifier: Development Status :: 5 - Production/Stable
Classifier: Operating System :: POSIX :: Linux
Classifier: Operating System :: MacOS :: MacOS X
Classifier: Operating System :: Microsoft :: Windows
Classifier: Topic :: Internet :: WWW/HTTP
Classifier: Topic :: Software Development :: Libraries :: Python Modules
Classifier: Framework :: AsyncIO
Requires-Dist: hopeit.engine>=0.28.1
Requires-Dist: aiofiles>=24.1.0
